{"title":"李彦宏卸任百度云执行董事 百度推进干部年轻化","source":" 2019-10-08 11:15:17　来源:   ","time":"中新经纬","content":"\n （原标题：李彦宏卸任百度云执行董事 百度加速干部年轻化进程） \n\n\n【#李彦宏卸任百度云执行董事#百度加速干部年轻化进程】天眼查数据显示，近日，百度云计算技术(北京)有限公司发生变更，百度创始人李彦宏卸任执行董事。同时，刘辉卸任总经理一职，新增崔珊珊为总经理、执行董事。\n\n\n\n\n\n搜索\"百度离职\":向海龙陷\"罗生门\" 陆奇仅供职一年 \n<https://news.163.com/19/0928/10/EQ5EESE30001899N.html>\n\n\n9月27日，腾讯深网在《揭秘百度新治理结构：马东敏的谣言与李彦宏的用人观》一文中援引百度高管称，向海龙是被开除的。但随后向海龙向媒体回应中否认了此事。针锋相对的说法引起外界围观。\n\n\n\n\n <> \n\n <http://news.163.com/> 本文来源：中新经纬 责任编辑：王宁_NB12468 "}